cdk_aws_iot_thing_certificate_policy_dev/__init__.py
cdk_aws_iot_thing_certificate_policy_dev/py.typed
cdk_aws_iot_thing_certificate_policy_dev/_jsii/__init__.py
cdk_aws_iot_thing_certificate_policy_dev/_jsii/cdk-aws-iot-thing-certificate-policy-dev@0.0.15.jsii.tgz
cdk_aws_iot_thing_certificate_policy_dev-0.0.15.dist-info/LICENSE
cdk_aws_iot_thing_certificate_policy_dev-0.0.15.dist-info/METADATA
cdk_aws_iot_thing_certificate_policy_dev-0.0.15.dist-info/WHEEL
cdk_aws_iot_thing_certificate_policy_dev-0.0.15.dist-info/top_level.txt
cdk_aws_iot_thing_certificate_policy_dev-0.0.15.dist-info/RECORD
