Metadata-Version: 2.1
Name: cdk-aws-iot-thing-certificate-policy-dev
Version: 0.0.15
Summary: Creates an AWS IoT thing, certificate, policy, and associates the three together
Home-page: https://github.com/gadams999/cdk-aws-iot-thing-certificate-policy.git
Author: Gavin Adams<gavinaws@amazon.com>
License: Apache-2.0
Project-URL: Source, https://github.com/gadams999/cdk-aws-iot-thing-certificate-policy.git
Classifier: Intended Audience :: Developers
Classifier: Operating System :: OS Independent
Classifier: Programming Language :: JavaScript
Classifier: Programming Language :: Python :: 3 :: Only
Classifier: Programming Language :: Python :: 3.8
Classifier: Programming Language :: Python :: 3.9
Classifier: Programming Language :: Python :: 3.10
Classifier: Programming Language :: Python :: 3.11
Classifier: Typing :: Typed
Classifier: Development Status :: 4 - Beta
Classifier: License :: OSI Approved
Requires-Python: ~=3.8
License-File: LICENSE
Requires-Dist: aws-cdk-lib <3.0.0,>=2.133.0
Requires-Dist: cdk-nag <3.0.0,>=2.28.63
Requires-Dist: constructs <11.0.0,>=10.0.5
Requires-Dist: jsii <2.0.0,>=1.95.0
Requires-Dist: publication >=0.0.3
Requires-Dist: typeguard ~=2.13.3
